ListenSay.py
listensay-0.0.1.dist-info/WHEEL
listensay-0.0.1.dist-info/METADATA
listensay-0.0.1.dist-info/RECORD
